mpcq-0.4.0.dist-info/METADATA
mpcq-0.4.0.dist-info/WHEEL
mpcq-0.4.0.dist-info/entry_points.txt
mpcq-0.4.0.dist-info/licenses/LICENSE.md
mpcq/__init__.py
mpcq/_version.py
mpcq/client.py
mpcq/observations.py
mpcq/orbits.py
mpcq/submissions.py
mpcq/tests/__init__.py
mpcq/tests/data/final_results.parquet
mpcq/tests/data/matched_results.parquet
mpcq/tests/test_client.py
mpcq/tests/test_cross_match.py
mpcq/tests/test_imports.py
mpcq-0.4.0.dist-info/RECORD
