Metadata-Version: 2.1
Name: mpcq
Version: 0.4.0
Summary: Client library for interacting with an MPC observations database
Keywords: astronomy,orbital mechanics,propagation
Author-Email: Spencer Nelson <spencer@b612foundation.org>, Nate Tellis <nate@b612foundation.org>, Alec Koumjian <alec@b612foundation.org>, Joachim Moeyens <moeyensj@uw.edu>
License: The MIT License (MIT)
Classifier: Operating System :: OS Independent
Classifier: Development Status :: 4 - Beta
Classifier: Intended Audience :: Science/Research
Classifier: License :: OSI Approved :: MIT License
Classifier: Programming Language :: Python
Classifier: Programming Language :: Python :: 3
Classifier: Topic :: Scientific/Engineering :: Astronomy
Project-URL: Documentation, https://github.com/B612-Asteroid-Institute/mpcq#README.md
Project-URL: Issues, https://github.com/B612-Asteroid-Institute/mpcq/issues
Project-URL: Source, https://github.com/B612-Asteroid-Institute/mpcq
Requires-Python: <3.13,>=3.11
Requires-Dist: adam_core>=0.2.5
Requires-Dist: astropy
Requires-Dist: google-cloud-bigquery
Requires-Dist: google-cloud-secret-manager
Requires-Dist: numpy
Requires-Dist: quivr
Requires-Dist: google-cloud-bigquery-storage>=2.27.0
Requires-Dist: tqdm>=4.67.1
Provides-Extra: dev
Requires-Dist: black; extra == "dev"
Requires-Dist: ipython; extra == "dev"
Requires-Dist: isort; extra == "dev"
Requires-Dist: mypy; extra == "dev"
Requires-Dist: pdm; extra == "dev"
Requires-Dist: pytest-benchmark; extra == "dev"
Requires-Dist: pytest-cov; extra == "dev"
Requires-Dist: pytest-doctestplus; extra == "dev"
Requires-Dist: pytest-mock; extra == "dev"
Requires-Dist: pytest; extra == "dev"
Requires-Dist: ruff; extra == "dev"
Requires-Dist: sphinx>=7.0.0; extra == "dev"
Requires-Dist: sphinx-rtd-theme>=2.0.0; extra == "dev"
Requires-Dist: myst-parser>=2.0.0; extra == "dev"
Requires-Dist: sphinx-autobuild; extra == "dev"
